checkkit/__init__.py
checkkit/main.py
tests/__init__.py
tests/main.py
checkkit-0.3.0.dist-info/LICENSE
checkkit-0.3.0.dist-info/METADATA
checkkit-0.3.0.dist-info/WHEEL
checkkit-0.3.0.dist-info/top_level.txt
checkkit-0.3.0.dist-info/RECORD
